bic_pptx_report_generator.py
bic_pptx_report_generator-0.1.0.dist-info/WHEEL
bic_pptx_report_generator-0.1.0.dist-info/METADATA
bic_pptx_report_generator-0.1.0.dist-info/RECORD
