Metadata-Version: 2.1
Name: bic-pptx-report-generator
Version: 0.1.0
Summary: Input folder with pictures and text files where the text files describe the pictures and are named to match the picture they describe. The folders are named what you want the slides to be named, and the names of the pictures match what you would want in the labels.
Author: Heather-BIC
Requires-Python: >=3.10,<4.0
Classifier: Programming Language :: Python :: 3
Classifier: Programming Language :: Python :: 3.10
Requires-Dist: PyAutoGUI (>=0.9.53,<0.10.0)
Requires-Dist: python-pptx (>=0.6.21,<0.7.0)
